{
  "project_info": {
    "project_number": "704860703186",
    "project_id": "learn-java-cf2db",
    "storage_bucket": "learn-java-cf2db.appspot.com"
  },
  "client": [
    {
      "client_info": {
        "mobilesdk_app_id": "1:704860703186:android:048e6132f0d74b5580a00b",
        "android_client_info": {
          "package_name": "com.example.learnjava"
        }
      },
      "oauth_client": [
        {
          "client_id": "704860703186-h42u6r8jmvh3dcf1kqqhrmgjhlm84pt6.apps.googleusercontent.com",
          "client_type": 3
        }
      ],
      "api_key": [
        {
          "current_key": "AIzaSyDtU25YjqrxhXF2ZHvPOgcemEhAs9cxgUU"
        }
      ],
      "services": {
        "appinvite_service": {
          "other_platform_oauth_client": [
            {
              "client_id": "704860703186-h42u6r8jmvh3dcf1kqqhrmgjhlm84pt6.apps.googleusercontent.com",
              "client_type": 3
            }
          ]
        }
      }
    }
  ],
  "configuration_version": "1"
}